fastapi_sqlmodel_crud/README.md
fastapi_sqlmodel_crud/__init__.py
fastapi_sqlmodel_crud/_sqlmodel.py
fastapi_sqlmodel_crud/base.py
fastapi_sqlmodel_crud/parser.py
fastapi_sqlmodel_crud/schema.py
fastapi_sqlmodel_crud/utils.py
fastapi_sqlmodel_crud-0.3.0.dist-info/WHEEL
fastapi_sqlmodel_crud-0.3.0.dist-info/METADATA
fastapi_sqlmodel_crud-0.3.0.dist-info/RECORD
