Metadata-Version: 2.1
Name: fastapi_sqlmodel_crud
Version: 0.3.0
Summary: fastapi-sqlmodel-crud is a program which is based on fastapi+sqlmodel and used to quickly build the Create, Read, Update, Delete generic API interface.
Keywords: sqlmodel,fastapi-sqlmodel-crud,fastapi-amis-admin,fastapi-crud,fastapi-sqlmodel
Author-email: Atomi <1456417373@qq.com>
Maintainer-email: Atomi <1456417373@qq.com>
Requires-Python: >=3.6.1
Classifier: Framework :: FastAPI
Classifier: Environment :: Web Environment
Classifier: Topic :: System :: Systems Administration
Classifier: License :: OSI Approved :: Apache Software License
Classifier: Operating System :: OS Independent
Classifier: Programming Language :: Python :: 3
Classifier: Programming Language :: Python :: 3.6
Classifier: Programming Language :: Python :: 3.7
Classifier: Programming Language :: Python :: 3.8
Classifier: Programming Language :: Python :: 3.9
Classifier: Programming Language :: Python :: 3.10
Requires-Dist: fastapi>=0.68.0
Requires-Dist: sqlmodel>=0.0.8
Requires-Dist: ujson>=4.0.1
Requires-Dist: sqlalchemy-database>=0.1.0,<0.2.0
Requires-Dist: pytest >=6.2.4,<7.0.0 ; extra == "test"
Requires-Dist: aiosqlite ; extra == "test"
Requires-Dist: pytest-asyncio>=0.17 ; extra == "test"
Requires-Dist: httpx ; extra == "test"
Project-URL: Documentation, https://docs.gh.amis.work/crud/SQLModelCrud/
Project-URL: FastAPI-Amis-Admin, https://github.com/amisadmin/fastapi_amis_admin
Project-URL: Source, https://github.com/amisadmin/fastapi_amis_admin
Provides-Extra: test
